pyflp/__init__.py
pyflp/_adapters.py
pyflp/_descriptors.py
pyflp/_events.py
pyflp/_models.py
pyflp/_version.py
pyflp/arrangement.py
pyflp/channel.py
pyflp/controller.py
pyflp/exceptions.py
pyflp/mixer.py
pyflp/pattern.py
pyflp/plugin.py
pyflp/project.py
pyflp/py.typed
pyflp/timemarker.py
pyflp/types.py
pyflp-2.2.1.dist-info/LICENSE
pyflp-2.2.1.dist-info/METADATA
pyflp-2.2.1.dist-info/WHEEL
pyflp-2.2.1.dist-info/top_level.txt
pyflp-2.2.1.dist-info/RECORD
