Metadata-Version: 2.1
Name: pyflp
Version: 2.2.1
Summary: FL Studio project file parser
Author-email: demberto <demberto@protonmail.com>
License: GPL-3.0
Project-URL: Source, https://github.com/demberto/PyFLP
Project-URL: Changelog, https://github.com/demberto/PyFLP/blob/master/CHANGELOG.md
Project-URL: Documentation, https://pyflp.rtfd.io
Project-URL: Bug Tracker, https://github.com/demberto/PyFLP/issues
Classifier: Development Status :: 3 - Alpha
Classifier: Intended Audience :: Developers
Classifier: License :: OSI Approved :: GNU General Public License v3 (GPLv3)
Classifier: Operating System :: OS Independent
Classifier: Programming Language :: Python :: 3 :: Only
Classifier: Programming Language :: Python :: 3.8
Classifier: Programming Language :: Python :: 3.9
Classifier: Programming Language :: Python :: 3.10
Classifier: Programming Language :: Python :: 3.11
Classifier: Programming Language :: Python :: Implementation :: CPython
Classifier: Programming Language :: Python :: Implementation :: PyPy
Classifier: Topic :: Multimedia
Classifier: Topic :: Software Development :: Libraries :: Python Modules
Classifier: Typing :: Typed
Requires-Python: >=3.8
Provides-Extra: dev
License-File: LICENSE
